main.py
haw/__init__.py
haw/haw.py
haw/data/__init__.py
haw/data/height_data.py
haw/data/para.py
haw/data/weight_data.py
haw-0.0.8.dist-info/METADATA
haw-0.0.8.dist-info/WHEEL
haw-0.0.8.dist-info/top_level.txt
haw-0.0.8.dist-info/RECORD
