Metadata-Version: 2.1
Name: haw
Version: 0.0.8
Summary: Package for the computation of height-adjusted weight scores
Author-email: Joao Kruse <soyjog@gmail.com>
Classifier: Programming Language :: Python :: 3
Classifier: License :: OSI Approved :: MIT License
Classifier: Operating System :: OS Independent
Requires-Python: >=3.9
Requires-Dist: numpy
Requires-Dist: scipy
Requires-Dist: matplotlib
Requires-Dist: pandas
